stackit/ske/__init__.py
stackit/ske/api/__init__.py
stackit/ske/api/default_api.py
stackit/ske/api_client.py
stackit/ske/api_response.py
stackit/ske/configuration.py
stackit/ske/exceptions.py
stackit/ske/models/__init__.py
stackit/ske/models/acl.py
stackit/ske/models/availability_zone.py
stackit/ske/models/cluster.py
stackit/ske/models/cluster_error.py
stackit/ske/models/cluster_status.py
stackit/ske/models/cluster_status_state.py
stackit/ske/models/create_kubeconfig_payload.py
stackit/ske/models/create_or_update_cluster_payload.py
stackit/ske/models/credentials_rotation_state.py
stackit/ske/models/cri.py
stackit/ske/models/dns.py
stackit/ske/models/extension.py
stackit/ske/models/get_provider_options_request_version_state.py
stackit/ske/models/hibernation.py
stackit/ske/models/hibernation_schedule.py
stackit/ske/models/idp.py
stackit/ske/models/image.py
stackit/ske/models/kubeconfig.py
stackit/ske/models/kubernetes.py
stackit/ske/models/kubernetes_version.py
stackit/ske/models/list_clusters_response.py
stackit/ske/models/login_kubeconfig.py
stackit/ske/models/machine.py
stackit/ske/models/machine_image.py
stackit/ske/models/machine_image_version.py
stackit/ske/models/machine_type.py
stackit/ske/models/maintenance.py
stackit/ske/models/maintenance_auto_update.py
stackit/ske/models/network.py
stackit/ske/models/nodepool.py
stackit/ske/models/nodepool_kubernetes.py
stackit/ske/models/observability.py
stackit/ske/models/provider_options.py
stackit/ske/models/runtime_error.py
stackit/ske/models/taint.py
stackit/ske/models/time_window.py
stackit/ske/models/volume.py
stackit/ske/models/volume_type.py
stackit/ske/py.typed
stackit/ske/rest.py
stackit_ske-1.5.0.dist-info/METADATA
stackit_ske-1.5.0.dist-info/WHEEL
stackit_ske-1.5.0.dist-info/licenses/LICENSE.md
stackit_ske-1.5.0.dist-info/licenses/NOTICE.txt
stackit_ske-1.5.0.dist-info/RECORD
